README.md
setup.py
PyCCAPT_Calibration.egg-info/PKG-INFO
PyCCAPT_Calibration.egg-info/SOURCES.txt
PyCCAPT_Calibration.egg-info/dependency_links.txt
PyCCAPT_Calibration.egg-info/namespace_packages.txt
PyCCAPT_Calibration.egg-info/not-zip-safe
PyCCAPT_Calibration.egg-info/requires.txt
PyCCAPT_Calibration.egg-info/top_level.txt
pyccapt/calibration_tools/__init__.py
pyccapt/calibration_tools/calibration.py
pyccapt/calibration_tools/data_loadcrop.py
pyccapt/calibration_tools/data_tools.py
pyccapt/calibration_tools/intractive_point_identification.py
pyccapt/calibration_tools/selectors_data.py
pyccapt/calibration_tools/tools.py
pyccapt/calibration_tools/variables.py
pyccapt/calibration_tools/widgets.py
pyccapt/mc/__init__.py
pyccapt/mc/mc_tools.py
pyccapt/tutorials/__init__.py
pyccapt/tutorials/__main__.py
pyccapt/tutorials/startup.py